BiEntropy-1.1.4.data/headers/bientropy.h
bientropy/__init__.py
bientropy/pybientropy.py
bientropy/demo.py
bientropy/cbientropy.cpython-34m.so
bientropy/benchmark.py
bientropy/testvectors.py
bientropy/.libs/libgmp-35b4ca60.so.3.3.3
bientropy/tests/__main__.py
bientropy/tests/__init__.py
bientropy/tests/test_suite.py
BiEntropy-1.1.4.dist-info/LICENSE.txt
BiEntropy-1.1.4.dist-info/WHEEL
BiEntropy-1.1.4.dist-info/top_level.txt
BiEntropy-1.1.4.dist-info/METADATA
BiEntropy-1.1.4.dist-info/RECORD
